ragwrapper/__init__.py
ragwrapper/exception.py
ragwrapper/ingestion.py
ragwrapper/rag.py
ragwrapper/utils.py
ragwrapper/data_ingestion/__init__.py
ragwrapper/data_ingestion/graphDB/__init__.py
ragwrapper/data_ingestion/relationalDB/__init__.py
ragwrapper/data_ingestion/vectorDB/__init__.py
ragwrapper/data_ingestion/vectorDB/Loading/__init__.py
ragwrapper/data_ingestion/vectorDB/Loading/data_loading.py
ragwrapper/data_ingestion/vectorDB/chunking/__init__.py
ragwrapper/data_ingestion/vectorDB/chunking/data_splitting.py
ragwrapper/data_ingestion/vectorDB/embedding/__init__.py
ragwrapper/data_ingestion/vectorDB/embedding/data_embeddings.py
ragwrapper/data_ingestion/vectorDB/indexing/__init__.py
ragwrapper/data_ingestion/vectorDB/indexing/data_indexing.py
ragwrapper/data_source_routing/__init__.py
ragwrapper/document_retrieval/__init__.py
ragwrapper/document_retrieval/document_retrieval.py
ragwrapper/query_transformation/__init__.py
ragwrapper/query_transformation/prompts_template.py
ragwrapper/query_transformation/query_transformation.py
ragwrapper/response_generation/__init__.py
ragwrapper/response_generation/response_generation.py
ragwrapper/response_generation/response_prompts_template.py
ragwrapper-0.0.3.dist-info/LICENSE
ragwrapper-0.0.3.dist-info/METADATA
ragwrapper-0.0.3.dist-info/WHEEL
ragwrapper-0.0.3.dist-info/top_level.txt
ragwrapper-0.0.3.dist-info/RECORD
