Metadata-Version: 2.1
Name: ragwrapper
Version: 0.0.3
Summary: A package for LLMOps related tasks
Home-page: https://github.com/keshavkmr48/LLMOps
Author: keshav Kumar
Author-email: keshavkmr076@gmail.com
License: Apache Software License
Project-URL: Bug Tracker, https://github.com/keshavkmr48/LLMOps/issues
Classifier: Programming Language :: Python :: 3
Classifier: License :: OSI Approved :: Apache Software License
Classifier: Operating System :: OS Independent
Requires-Python: >=3.10
License-File: LICENSE
Requires-Dist: setuptools==75.2.0
Requires-Dist: wheel==0.44.0
Requires-Dist: autocommand==2.2.2
Requires-Dist: backports.tarfile==1.2.0
Requires-Dist: importlib-metadata==8.0.0
Requires-Dist: importlib-resources==6.4.0
Requires-Dist: inflect==7.3.1
Requires-Dist: jaraco.collections==5.1.0
Requires-Dist: jaraco.context==5.3.0
Requires-Dist: jaraco.functools==4.0.1
Requires-Dist: jaraco.text==3.12.1
Requires-Dist: more-itertools==10.3.0
Requires-Dist: packaging==24.1
Requires-Dist: platformdirs==4.2.2
Requires-Dist: tomli==2.0.1
Requires-Dist: typeguard==4.3.0
Requires-Dist: typing-extensions==4.12.2
Requires-Dist: zipp==3.19.2
Provides-Extra: testing
Requires-Dist: pytest>=7.1.3; extra == "testing"
Requires-Dist: mypy>=0.971; extra == "testing"
Requires-Dist: flake8>=5.0.4; extra == "testing"
Requires-Dist: tox>=3.25.1; extra == "testing"
Requires-Dist: black>=22.8.0; extra == "testing"
